Metadata-Version: 1.1
Name: hgreview
Version: 0.4
Summary: Mercurial extension to work with rietveld codereview
Home-page: https://bitbucket.org/nicoe/hgreview/
Author: B2CK
Author-email: info@b2ck.com
License: GPL-3
Download-URL: https://bitbucket.org/nicoe/hgreview/downloads
Platform: UNKNOWN
Classifier: Development Status :: 5 - Production/Stable
Classifier: Environment :: Plugins
Classifier: Intended Audience :: Developers
Classifier: License :: OSI Approved :: GNU General Public License (GPL)
Classifier: Operating System :: OS Independent
Classifier: Programming Language :: Python
Classifier: Topic :: Software Development :: Version Control
